cli.py
data_collector.py
filter_anomalous_data.py
preprocess_data.py
realtime_detector.py
train_autoencoder.py
prometheus_anomaly_detection_lstm-0.2.6.dist-info/licenses/LICENSE
prometheus_anomaly_detection_lstm-0.2.6.dist-info/METADATA
prometheus_anomaly_detection_lstm-0.2.6.dist-info/WHEEL
prometheus_anomaly_detection_lstm-0.2.6.dist-info/entry_points.txt
prometheus_anomaly_detection_lstm-0.2.6.dist-info/top_level.txt
prometheus_anomaly_detection_lstm-0.2.6.dist-info/RECORD
